palmero.py
palmero-0.2.3.dist-info/LICENSE
palmero-0.2.3.dist-info/METADATA
palmero-0.2.3.dist-info/WHEEL
palmero-0.2.3.dist-info/top_level.txt
palmero-0.2.3.dist-info/RECORD
